kwargs/__init__.py
tests/__init__.py
tests/test_kwargs.py
kwargs-1.0.1.dist-info/LICENSE
kwargs-1.0.1.dist-info/METADATA
kwargs-1.0.1.dist-info/WHEEL
kwargs-1.0.1.dist-info/top_level.txt
kwargs-1.0.1.dist-info/RECORD
