Metadata-Version: 2.1
Name: kwargs
Version: 1.0.1
Summary: Python micro-framework
Home-page: https://github.com/JakubTesarek/kwargs
Author: Jakub Tesárek
Author-email: jakub@tesarek.me
License: GNU GPL v2
Keywords: framework
Platform: UNKNOWN
Classifier: Development Status :: 3 - Alpha
Classifier: License :: OSI Approved :: GNU General Public License v2 (GPLv2)
Provides-Extra: test
